{"kind":"RoleBinding","apiVersion":"authorization.openshift.io/v1","metadata":{"name":"system:deployers","namespace":"openshift-sdn","selfLink":"/apis/authorization.openshift.io/v1/namespaces/openshift-sdn/rolebindings/system%3Adeployers","uid":"a03e6b2b-a715-11e9-9411-42010a9e0002","resourceVersion":"1247","creationTimestamp":"2019-07-15T15:31:33Z","annotations":{"openshift.io/description":"Allows deploymentconfigs in this namespace to rollout pods in this namespace.  It is auto-managed by a controller; remove subjects to disable."}},"userNames":["system:serviceaccount:openshift-sdn:deployer"],"groupNames":null,"subjects":[{"kind":"ServiceAccount","namespace":"openshift-sdn","name":"deployer"}],"roleRef":{"name":"system:deployer"}}
